femtoapiwrap/__init__.py
femtoapiwrap/_version.py
femtoapiwrap/api.py
femtoapiwrap/errors.py
femtoapiwrap/utils.py
femtoapiwrap/hi/__init__.py
femtoapiwrap/hi/_highapi.py
femtoapiwrap/hi/_mescfile.py
femtoapiwrap-0.5.4.dist-info/LICENSE.txt
femtoapiwrap-0.5.4.dist-info/METADATA
femtoapiwrap-0.5.4.dist-info/WHEEL
femtoapiwrap-0.5.4.dist-info/top_level.txt
femtoapiwrap-0.5.4.dist-info/RECORD
