Metadata-Version: 2.1
Name: femtoapiwrap
Version: 0.5.4
Summary: FemtoAPI Python wrapper
Home-page: https://femtonics.eu
Author: Femtonics Ltd.
Author-email: support@femtonics.eu
License: GNU General Public License v2 (GPLv2)
Keywords: FemtoAPI
Platform: UNKNOWN
Classifier: Programming Language :: Python :: 3.8
Classifier: Development Status :: 4 - Beta
Classifier: Intended Audience :: Science/Research
Classifier: License :: OSI Approved :: GNU General Public License v2 (GPLv2)
Classifier: Operating System :: Microsoft :: Windows :: Windows 10
Classifier: Topic :: Scientific/Engineering
Classifier: Typing :: Typed
Requires-Python: <=3.8.13,>=3.8
Requires-Dist: femtoapi (==1.0.0)
Requires-Dist: PySide2
Requires-Dist: numpy
Requires-Dist: scipy (>=1.2.0)
Requires-Dist: upolygon (==0.1.8)
Provides-Extra: doc
Requires-Dist: sphinx ; extra == 'doc'
Requires-Dist: docutils (==0.18.1) ; extra == 'doc'
Requires-Dist: sphinx-rtd-theme ; extra == 'doc'
Provides-Extra: examples
Requires-Dist: h5py ; extra == 'examples'
Requires-Dist: Pillow (==9.1.1) ; extra == 'examples'
Requires-Dist: matplotlib ; extra == 'examples'
Provides-Extra: test
Requires-Dist: coverage ; extra == 'test'
